__init__.py
mpg_cloud.py
seafile.py
mpg_cloud.egg-info/PKG-INFO
mpg_cloud.egg-info/SOURCES.txt
mpg_cloud.egg-info/dependency_links.txt
mpg_cloud.egg-info/requires.txt
mpg_cloud.egg-info/top_level.txt
mpg_cloud-1.0.1.dist-info/METADATA
mpg_cloud-1.0.1.dist-info/WHEEL
mpg_cloud-1.0.1.dist-info/top_level.txt
mpg_cloud-1.0.1.dist-info/RECORD
