Metadata-Version: 2.1
Name: mpg-cloud
Version: 1.0.1
Summary: Manage files in MPG Cloudservices.
Home-page: https://gitlab.gwdg.de/hbenne/mpg_cloud.git
Author: Hannes Benne
Author-email: hbenne@mpiwg-berlin.mpg.de
License: MIT
Platform: UNKNOWN
Classifier: License :: OSI Approved :: MIT License
Classifier: Programming Language :: Python :: 3
Classifier: Programming Language :: Python :: 3.6
Requires-Dist: lxml
Requires-Dist: beautifulsoup4
Requires-Dist: requests
